paradox/__init__.py
paradox/config.py
paradox/event.py
paradox/exceptions.py
paradox/main.py
paradox/paradox.py
paradox/connections/__init__.py
paradox/connections/connection.py
paradox/connections/handler.py
paradox/connections/protocols.py
paradox/connections/serial_connection.py
paradox/connections/ip/__init__.py
paradox/connections/ip/commands.py
paradox/connections/ip/connection.py
paradox/connections/ip/parsers.py
paradox/connections/ip/stun_session.py
paradox/console_scripts/__init__.py
paradox/console_scripts/ip150_connection_decrypt.py
paradox/console_scripts/pai_dump_memory.py
paradox/console_scripts/pai_run.py
paradox/data/__init__.py
paradox/data/element_type_container.py
paradox/data/enums.py
paradox/data/memory_storage.py
paradox/data/model.py
paradox/hardware/__init__.py
paradox/hardware/common.py
paradox/hardware/panel.py
paradox/hardware/parsers.py
paradox/hardware/evo/__init__.py
paradox/hardware/evo/adapters.py
paradox/hardware/evo/event.py
paradox/hardware/evo/panel.py
paradox/hardware/evo/parsers.py
paradox/hardware/evo/property.py
paradox/hardware/evo/models/__init__.py
paradox/hardware/evo/models/evo192.py
paradox/hardware/evo/models/evo48.py
paradox/hardware/evo/models/evo96.py
paradox/hardware/evo/models/evohd.py
paradox/hardware/spectra_magellan/__init__.py
paradox/hardware/spectra_magellan/adapters.py
paradox/hardware/spectra_magellan/event.py
paradox/hardware/spectra_magellan/panel.py
paradox/hardware/spectra_magellan/parsers.py
paradox/hardware/spectra_magellan/property.py
paradox/interfaces/__init__.py
paradox/interfaces/interface_manager.py
paradox/interfaces/ip_interface/__init__.py
paradox/interfaces/ip_interface/client_connection.py
paradox/interfaces/ip_interface/interface.py
paradox/interfaces/mqtt/__init__.py
paradox/interfaces/mqtt/basic.py
paradox/interfaces/mqtt/core.py
paradox/interfaces/mqtt/helpers.py
paradox/interfaces/mqtt/homeassistant.py
paradox/interfaces/mqtt/entities/__init__.py
paradox_alarm_interface-3.7.0.dist-info/licenses/LICENSE
paradox_alarm_interface-3.7.0.dist-info/METADATA
paradox_alarm_interface-3.7.0.dist-info/WHEEL
paradox_alarm_interface-3.7.0.dist-info/entry_points.txt
paradox_alarm_interface-3.7.0.dist-info/top_level.txt
paradox_alarm_interface-3.7.0.dist-info/zip-safe
paradox_alarm_interface-3.7.0.dist-info/RECORD
