Metadata-Version: 2.4
Name: paradox-alarm-interface
Version: 3.7.0
Summary: Interface to Paradox Alarm Panels
Home-page: https://github.com/ParadoxAlarmInterface/pai
Author: Jevgeni Kiski, João Paulo Barraca
Author-email: yozik04@gmail.com, jpbarraca@gmail.com
License: EPL
Project-URL: Bug Tracker, https://github.com/ParadoxAlarmInterface/pai/issues
Keywords: paradox alarm ip150 serial home-assistant smarthome mqtt
Classifier: Development Status :: 5 - Production/Stable
Classifier: Intended Audience :: Developers
Classifier: License :: OSI Approved :: Eclipse Public License 2.0 (EPL-2.0)
Classifier: Operating System :: OS Independent
Classifier: Programming Language :: Python
Classifier: Programming Language :: Python :: 3 :: Only
Classifier: Programming Language :: Python :: 3.8
Classifier: Programming Language :: Python :: 3.9
Classifier: Programming Language :: Python :: 3.10
Classifier: Programming Language :: Python :: 3.11
Requires-Python: <3.12,>=3.8
License-File: LICENSE
Requires-Dist: construct~=2.9.43
Requires-Dist: argparse>=1.4.0
Requires-Dist: python-slugify>=4.0.1
Requires-Dist: pytz>=2021.3
Requires-Dist: paho_mqtt<2,>=1.5.0
Requires-Dist: requests>=2.20.0
Requires-Dist: pyserial-asyncio>=0.4
Provides-Extra: yaml
Requires-Dist: pyyaml>=5.2.0; extra == "yaml"
Provides-Extra: pushbullet
Requires-Dist: pushbullet.py>=0.11.0; extra == "pushbullet"
Requires-Dist: ws4py>=0.4.2; extra == "pushbullet"
Provides-Extra: signal
Requires-Dist: pygobject>=3.20.0; extra == "signal"
Requires-Dist: pydbus>=0.6.0; extra == "signal"
Requires-Dist: gi>=1.2; extra == "signal"
Dynamic: license-file
